linkedin_job_scraper/__init__.py
linkedin_job_scraper/job.py
linkedin_job_scraper/job_search.py
linkedin_job_scraper/scraping_utils.py
tests/__init__.py
tests/test_job_search.py
linkedin_job_scraper-0.0.2.dist-info/LICENSE
linkedin_job_scraper-0.0.2.dist-info/METADATA
linkedin_job_scraper-0.0.2.dist-info/WHEEL
linkedin_job_scraper-0.0.2.dist-info/top_level.txt
linkedin_job_scraper-0.0.2.dist-info/RECORD
