Metadata-Version: 2.1
Name: linkedin_job_scraper
Version: 0.0.2
Summary: Web scraper of jobs from LinkedIn
Home-page: https://github.com/iliadzen/linkedin_job_scraper
Author: Ilia Zenin
Author-email: iliazenin.msu@gmail.com
License-File: LICENSE
Requires-Dist: selenium ==4.23.1
Requires-Dist: requests ==2.32.3
Requires-Dist: pytest ==8.3.2
Requires-Dist: beautifulsoup4 ==4.12.3
